{"_ts":[1546319688,1546363221,1546407367,1546451068,1546495202],"_r":{"breakdown":{"html":{"bytes":[56465,56446,56447,56451,56458],"requests":[31,31,31,31,31]},"js":{"bytes":[210725,210781,210725,210729,210738],"requests":[3,3,3,3,3]},"css":{"bytes":[2143,2087,2143,2143,2144],"requests":[2,2,2,2,2]},"image":{"bytes":[1857716,1856623,1856449,1857643,1857643],"requests":[35,34,35,35,35]},"flash":{"bytes":[0,0,0,0,0],"requests":[0,0,0,0,0]},"font":{"bytes":[14827,14827,14827,14827,14827],"requests":[1,1,1,1,1]},"video":{"bytes":[0,0,0,0,0],"requests":[0,0,0,0,0]},"other":{"bytes":[13469,13306,13476,13435,13462],"requests":[10,10,10,10,10]}},"date":[1546319688,1546363221,1546407367,1546451068,1546495202],"domElements":[109,null,109,109,109],"domInteractive":[779,null,578,722,676],"firstPaint":[523.199999996,null,446.299999996,437.4000000025,578.3999999985],"fullyLoaded":[3981,null,3924,3925,4181],"id":["190101_2K_40e96a1ac6248d07dd5b58825a687650","190101_8F_3d721deb1cbb7f9f0017e1a54f9f6736","190102_VA_3fe6c176b71f93a51140e3cb86421872","190102_9P_801f80bdd79bd9d22cb1d6973ff96b75","190103_FE_034e33a0a492186ae33b03112a495c82"],"loadTime":[2019,null,2172,2191,2372],"render":[600,null,400,400,800],"SpeedIndex":[1244,null,1052,1042,1424],"TTFB":[240,null,236,224,282],"videoFrames":[[{"_i":"ms_000000.jpg","_t":0,"_vc":0},{"_i":"ms_000600.jpg","_t":600,"_vc":50},{"_i":"ms_000700.jpg","_t":700,"_vc":57},{"_i":"ms_000800.jpg","_t":800,"_vc":47},{"_i":"ms_000900.jpg","_t":900,"_vc":51},{"_i":"ms_001000.jpg","_t":1000,"_vc":51},{"_i":"ms_001100.jpg","_t":1100,"_vc":51},{"_i":"ms_001200.jpg","_t":1200,"_vc":51},{"_i":"ms_001300.jpg","_t":1300,"_vc":51},{"_i":"ms_001400.jpg","_t":1400,"_vc":51},{"_i":"ms_001500.jpg","_t":1500,"_vc":51},{"_i":"ms_001600.jpg","_t":1600,"_vc":51},{"_i":"ms_001700.jpg","_t":1700,"_vc":51},{"_i":"ms_001800.jpg","_t":1800,"_vc":82},{"_i":"ms_001900.jpg","_t":1900,"_vc":61},{"_i":"ms_002000.jpg","_t":2000,"_vc":100}],[{"_i":"ms_000000.jpg","_t":0,"_vc":0},{"_i":"ms_000500.jpg","_t":500,"_vc":50},{"_i":"ms_000700.jpg","_t":700,"_vc":56},{"_i":"ms_000800.jpg","_t":800,"_vc":57},{"_i":"ms_000900.jpg","_t":900,"_vc":52},{"_i":"ms_001000.jpg","_t":1000,"_vc":52},{"_i":"ms_001100.jpg","_t":1100,"_vc":51},{"_i":"ms_001200.jpg","_t":1200,"_vc":51},{"_i":"ms_001300.jpg","_t":1300,"_vc":51},{"_i":"ms_001400.jpg","_t":1400,"_vc":51},{"_i":"ms_001500.jpg","_t":1500,"_vc":51},{"_i":"ms_001600.jpg","_t":1600,"_vc":51},{"_i":"ms_001700.jpg","_t":1700,"_vc":61},{"_i":"ms_002100.jpg","_t":2100,"_vc":100}],[{"_i":"ms_000000.jpg","_t":0,"_vc":0},{"_i":"ms_000400.jpg","_t":400,"_vc":50},{"_i":"ms_000500.jpg","_t":500,"_vc":57},{"_i":"ms_000700.jpg","_t":700,"_vc":44},{"_i":"ms_000800.jpg","_t":800,"_vc":48},{"_i":"ms_000900.jpg","_t":900,"_vc":48},{"_i":"ms_001000.jpg","_t":1000,"_vc":48},{"_i":"ms_001100.jpg","_t":1100,"_vc":48},{"_i":"ms_001200.jpg","_t":1200,"_vc":79},{"_i":"ms_001300.jpg","_t":1300,"_vc":82},{"_i":"ms_001400.jpg","_t":1400,"_vc":82},{"_i":"ms_001500.jpg","_t":1500,"_vc":61},{"_i":"ms_002000.jpg","_t":2000,"_vc":100}],[{"_i":"ms_000000.jpg","_t":0,"_vc":0},{"_i":"ms_000400.jpg","_t":400,"_vc":50},{"_i":"ms_000500.jpg","_t":500,"_vc":57},{"_i":"ms_000600.jpg","_t":600,"_vc":81},{"_i":"ms_000700.jpg","_t":700,"_vc":81},{"_i":"ms_000800.jpg","_t":800,"_vc":47},{"_i":"ms_000900.jpg","_t":900,"_vc":47},{"_i":"ms_001000.jpg","_t":1000,"_vc":47},{"_i":"ms_001100.jpg","_t":1100,"_vc":47},{"_i":"ms_001200.jpg","_t":1200,"_vc":47},{"_i":"ms_001300.jpg","_t":1300,"_vc":47},{"_i":"ms_001400.jpg","_t":1400,"_vc":47},{"_i":"ms_001500.jpg","_t":1500,"_vc":48},{"_i":"ms_001600.jpg","_t":1600,"_vc":51},{"_i":"ms_001700.jpg","_t":1700,"_vc":94},{"_i":"ms_001800.jpg","_t":1800,"_vc":94},{"_i":"ms_001900.jpg","_t":1900,"_vc":91},{"_i":"ms_002200.jpg","_t":2200,"_vc":100}],[{"_i":"ms_000000.jpg","_t":0,"_vc":0},{"_i":"ms_000800.jpg","_t":800,"_vc":50},{"_i":"ms_000900.jpg","_t":900,"_vc":45},{"_i":"ms_001000.jpg","_t":1000,"_vc":46},{"_i":"ms_001100.jpg","_t":1100,"_vc":48},{"_i":"ms_001200.jpg","_t":1200,"_vc":48},{"_i":"ms_001300.jpg","_t":1300,"_vc":49},{"_i":"ms_001400.jpg","_t":1400,"_vc":49},{"_i":"ms_001500.jpg","_t":1500,"_vc":49},{"_i":"ms_001600.jpg","_t":1600,"_vc":49},{"_i":"ms_001700.jpg","_t":1700,"_vc":51},{"_i":"ms_001800.jpg","_t":1800,"_vc":51},{"_i":"ms_001900.jpg","_t":1900,"_vc":82},{"_i":"ms_002000.jpg","_t":2000,"_vc":82},{"_i":"ms_002100.jpg","_t":2100,"_vc":82},{"_i":"ms_002200.jpg","_t":2200,"_vc":95},{"_i":"ms_002300.jpg","_t":2300,"_vc":100}]],"visualComplete":[2000,null,2000,2200,2300],"lighthouse":[85,null,85,85,85],"pagespeed":[92,92,92,92,92]}}